{
    "output": {
        "blocklist": [],
        "crystalizer#0": {
            "band0": {
                "bypass": true,
                "intensity": -40.0,
                "mute": false
            },
            "band1": {
                "bypass": true,
                "intensity": -40.0,
                "mute": false
            },
            "band10": {
                "bypass": false,
                "intensity": -14.0,
                "mute": false
            },
            "band11": {
                "bypass": false,
                "intensity": -7.0,
                "mute": false
            },
            "band12": {
                "bypass": false,
                "intensity": -16.0,
                "mute": false
            },
            "band2": {
                "bypass": true,
                "intensity": -40.0,
                "mute": false
            },
            "band3": {
                "bypass": true,
                "intensity": -40.0,
                "mute": false
            },
            "band4": {
                "bypass": true,
                "intensity": -40.0,
                "mute": false
            },
            "band5": {
                "bypass": true,
                "intensity": -40.0,
                "mute": false
            },
            "band6": {
                "bypass": true,
                "intensity": -40.0,
                "mute": false
            },
            "band7": {
                "bypass": true,
                "intensity": -40.0,
                "mute": false
            },
            "band8": {
                "bypass": true,
                "intensity": -40.0,
                "mute": false
            },
            "band9": {
                "bypass": false,
                "intensity": -13.0,
                "mute": false
            },
            "bypass": false,
            "input-gain": 0.0,
            "output-gain": 0.0
        },
        "equalizer#1": {
            "balance": 0.0,
            "bypass": false,
            "input-gain": 2.0,
            "left": {
                "band0": {
                    "frequency": 60.0,
                    "gain": 2.000000238418579,
                    "mode": "RLC (BT)",
                    "mute": false,
                    "q": 4.0,
                    "slope": "x4",
                    "solo": false,
                    "type": "Bell",
                    "width": 4.0
                },
                "band1": {
                    "frequency": 1000.0,
                    "gain": -9.5,
                    "mode": "RLC (MT)",
                    "mute": false,
                    "q": 2.42861286636753e-17,
                    "slope": "x1",
                    "solo": false,
                    "type": "Bell",
                    "width": 4.0
                },
                "band2": {
                    "frequency": 11000.0,
                    "gain": 6.0,
                    "mode": "RLC (BT)",
                    "mute": false,
                    "q": 1.5,
                    "slope": "x4",
                    "solo": false,
                    "type": "Bell",
                    "width": 4.0
                }
            },
            "mode": "IIR",
            "num-bands": 3,
            "output-gain": 0.0,
            "pitch-left": 0.0,
            "pitch-right": 0.0,
            "right": {
                "band0": {
                    "frequency": 60.0,
                    "gain": 2.000000238418579,
                    "mode": "RLC (BT)",
                    "mute": false,
                    "q": 4.0,
                    "slope": "x4",
                    "solo": false,
                    "type": "Bell",
                    "width": 4.0
                },
                "band1": {
                    "frequency": 1000.0,
                    "gain": -9.5,
                    "mode": "RLC (MT)",
                    "mute": false,
                    "q": 2.42861286636753e-17,
                    "slope": "x1",
                    "solo": false,
                    "type": "Bell",
                    "width": 4.0
                },
                "band2": {
                    "frequency": 11000.0,
                    "gain": 6.0,
                    "mode": "RLC (BT)",
                    "mute": false,
                    "q": 1.5,
                    "slope": "x4",
                    "solo": false,
                    "type": "Bell",
                    "width": 4.0
                }
            },
            "split-channels": false
        },
        "plugins_order": [
            "equalizer#1",
            "crystalizer#0"
        ]
    }
}
