{
    "input": {
        "autogain#0": {
            "bypass": false,
            "input-gain": 0.0,
            "maximum-history": 6,
            "output-gain": 0.0,
            "reference": "Geometric Mean (MSI)",
            "silence-threshold": -70.0,
            "target": -40.0
        },
        "blocklist": [],
        "deepfilternet#0": {
            "attenuation-limit": 100.0,
            "max-df-processing-threshold": 20.0,
            "max-erb-processing-threshold": 30.0,
            "min-processing-buffer": 10,
            "min-processing-threshold": -10.0,
            "post-filter-beta": 0.05
        },
        "deesser#0": {
            "bypass": false,
            "detection": "Peak",
            "f1-freq": 6000.0,
            "f1-level": 0.0,
            "f2-freq": 8500.0,
            "f2-level": 8.000000000000016,
            "f2-q": 1.0,
            "input-gain": 0.0,
            "laxity": 30,
            "makeup": 0.0,
            "mode": "Wide",
            "output-gain": 0.0,
            "ratio": 20.0,
            "sc-listen": false,
            "threshold": -30.300000000000175
        },
        "plugins_order": [
            "deepfilternet#0",
            "autogain#0",
            "deesser#0"
        ]
    }
}
